croissant/__init__.py
croissant/beam.py
croissant/constants.py
croissant/dpss.py
croissant/healpix.py
croissant/rotations.py
croissant/simulator.py
croissant/sky.py
croissant/sphtransform.py
tests/__init__.py
tests/test_beam.py
tests/test_dpss.py
tests/test_healpix.py
tests/test_rotations.py
tests/test_simulator.py
tests/test_sphtransform.py
croissant_sim-3.0.0.dist-info/LICENSE
croissant_sim-3.0.0.dist-info/METADATA
croissant_sim-3.0.0.dist-info/WHEEL
croissant_sim-3.0.0.dist-info/top_level.txt
croissant_sim-3.0.0.dist-info/RECORD
