Metadata-Version: 2.1
Name: croissant-sim
Version: 3.0.0
Summary: CROISSANT: Rapid spherical harmonics-based simulator of visibilities
Home-page: https://github.com/christianhbye/croissant
Author: Christian Hellum Bye
Author-email: chbye@berkeley.edu
License: GPLv2
Classifier: Intended Audience :: Science/Research
Classifier: License :: OSI Approved :: GNU General Public License v2 or later (GPLv2+)
Classifier: Programming Language :: Python :: 3
Classifier: Topic :: Scientific/Engineering :: Astronomy
Requires-Python: >=3.7
License-File: LICENSE
Requires-Dist: astropy
Requires-Dist: healpy
Requires-Dist: hera-filters
Requires-Dist: jupyter
Requires-Dist: lunarsky
Requires-Dist: matplotlib
Requires-Dist: numpy
Requires-Dist: scipy
Provides-Extra: dev
Requires-Dist: black ; extra == 'dev'
Requires-Dist: build ; extra == 'dev'
Requires-Dist: flake8 ; extra == 'dev'
Requires-Dist: mypy ; extra == 'dev'
Requires-Dist: pytest ; extra == 'dev'
Requires-Dist: pytest-cov ; extra == 'dev'
Requires-Dist: twine ; extra == 'dev'
Provides-Extra: hera_sim
Requires-Dist: hera-sim[vis] ; extra == 'hera_sim'
